{"allPages":434,"data":[{"res":"","scr":"240x320","icon":"/mrp-icon/C5TL.png","label":"梦幻！欲望格斗","version":1001,"down":"/mrp-files/399285_240320_gywgd.mrp","size":"381.47KB","len":390630,"vendor":"杭州斯比","name":"gywgd.mrp","resLen":0,"resInfo":"","resSize":"","id":399285,"detail":"这是一所鱼龙混杂的流氓学校，各种黑暗势力笼罩着整个校园……"},{"res":"","scr":"240x320","icon":"/mrp-icon/2.png","label":"梦幻宝石","version":1017,"down":"/mrp-files/opmhbs.mrp","size":"105.71KB","len":108252,"vendor":"杭州斯凯","name":"lines.mrp","resLen":0,"resInfo":"","resSize":"","id":2,"detail":"经典的游戏，每款手机的必备游戏，重温儿时的精彩！"},{"res":"","scr":"240x320","icon":"/mrp-icon/2.png","label":"梦幻宝石","version":109,"down":"/mrp-files/lines.mrp","size":"79.34KB","len":81244,"vendor":"杭州斯凯","name":"lines.mrp","resLen":0,"resInfo":"","resSize":"","id":2,"detail":"益智游戏。"},{"res":"","scr":"240x320","icon":"/mrp-icon/2.png","label":"梦幻宝石","version":119,"down":"/mrp-files/opmhbs_mr.mrp","size":"82.54KB","len":84517,"vendor":"杭州斯凯","name":"lines.mrp","resLen":0,"resInfo":"","resSize":"","id":2,"detail":"益智游戏。"},{"res":"","scr":"240x320","icon":"/mrp-icon/C6N5.png","label":"梦幻封神","version":1,"down":"/mrp-files/1011_240320_gmhfs.mrp","size":"110.89KB","len":113547,"vendor":"斯凯","name":"gmhfs.mrp","resLen":0,"resInfo":"","resSize":"","id":1011,"detail":"梦幻封神"}],"now":225}