{"allPages":436,"data":[{"res":"","scr":"240x320","icon":"/mrp-icon/C6BV.png","label":"激情热舞","version":1003,"down":"/mrp-files/399743_240320_gjqrw.mrp","size":"263.99KB","len":270326,"vendor":"北京华信鼎天","name":"gjqrw.mrp","resLen":0,"resInfo":"","resSize":"","id":399743,"detail":"3D人物、操作简单、流行歌曲应有尽有，让音乐写下你的小小心动！"},{"res":"","scr":"240x320","icon":"/mrp-icon/C6N5.png","label":"极品成人笑话","version":1003,"down":"/mrp-files/opjpxh.mrp","size":"230.12KB","len":235646,"vendor":"深圳补天","name":"opjpxh.mrp","resLen":0,"resInfo":"","resSize":"","id":830117,"detail":"极品笑话"},{"res":"","scr":"240x320","icon":"/mrp-icon/C6N5.png","label":"极品飞车","version":1111,"down":"/mrp-files/jipinfeiche-wuyekuangbiaoGJPFC.MRP","size":"146.77KB","len":150288,"vendor":"杭州斯凯","name":"gjpfc.mrp","resLen":0,"resInfo":"","resSize":"","id":302007,"detail":"《极品飞车》画面精美，手感优秀，赛道丰富多样，道具种类繁多"},{"res":"","scr":"240x320","icon":"/mrp-icon/9OG6.png","label":"极品飞车MAX","version":1020,"down":"/mrp-files/320006_240320_gjpfcm.mrp","size":"393.81KB","len":403264,"vendor":"杭州斯凯","name":"gjpfcm.mrp","resLen":0,"resInfo":"","resSize":"","id":320006,"detail":"超炫的画面，强大的视觉冲击，让你在热血沸腾的赛车世界里极速狂飙"},{"res":"","scr":"240x320","icon":"/mrp-icon/9KKU.png","label":"极品家丁-9527","version":1003,"down":"/mrp-files/316062_240320_gjpjd.mrp","size":"437.89KB","len":448401,"vendor":"畅乐互动","name":"gjpjd.mrp","resLen":0,"resInfo":"","resSize":"","id":316062,"detail":"财团首富、如花美眷，看小小家丁，如何玩转官场、商场和情场！"}],"now":156}