{"allPages":436,"data":[{"res":"","scr":"240x320","icon":"/mrp-icon/C6N5.png","label":"武状元苏乞儿","version":1015,"down":"/mrp-files/390239_240320_gwzysqe.mrp","size":"445.67KB","len":456366,"vendor":"南京颂歌","name":"gwzysqe.mrp","resLen":0,"resInfo":"","resSize":"","id":390239,"detail":"英雄美女的浪漫传奇，轻松爆笑的幽默故事从这里开始。"},{"res":"","scr":"240x320","icon":"/mrp-icon/9VB4.png","label":"五虎上将子龙传","version":1008,"down":"/mrp-files/327012_240320_gwhzlz.mrp","size":"315.65KB","len":323225,"vendor":"SphinxJoy","name":"gwhzlz.mrp","resLen":0,"resInfo":"","resSize":"","id":327012,"detail":"三国将如云，子龙独逸群。武能擒上将，智足愧谋臣。"},{"res":"","scr":"240x320","icon":"/mrp-icon/C6N5.png","label":"五一带你玩转不停","version":3000,"down":"/mrp-files/398790_240320_mswzwy.mrp","size":"42.25KB","len":43267,"vendor":"sky","name":"mswzwy.mrp","resLen":0,"resInfo":"","resSize":"","id":398790,"detail":"五一狂欢，带你玩转不停，你玩游戏我付钱！游无止境，戏有精彩。"},{"res":"","scr":"240x320","icon":"/mrp-icon/C6N5.png","label":"午夜连连看","version":1026,"down":"/mrp-files/322007_240320_gjyllk.mrp","size":"317.18KB","len":324797,"vendor":"杭州斯比","name":"gjyllk.mrp","resLen":0,"resInfo":"","resSize":"","id":322007,"detail":"午夜连连看。"},{"res":"","scr":"240x320","icon":"/mrp-icon/96UA.png","label":"午夜台球2-冠军赛","version":1130,"down":"/mrp-files/302026_240320_gtq.mrp","size":"295.81KB","len":302907,"vendor":"杭州斯凯","name":"gtq.mrp","resLen":0,"resInfo":"","resSize":"","id":302026,"detail":"午夜台球，经典再现！让您体验畅快淋漓的运动享受。"}],"now":350}