{"allPages":436,"data":[{"res":"","scr":"240x320","icon":"/mrp-icon/C6N5.png","label":"把美女灌醉","version":1113,"down":"/mrp-files/opmmaa.mrp","size":"298.52KB","len":305683,"vendor":"斯凯","name":"opmmaa.mrp","resLen":0,"resInfo":"","resSize":"","id":830459,"detail":"flash应用"},{"res":"","scr":"240x320","icon":"/mrp-icon/C65E.png","label":"霸业之妻妾成群","version":1003,"down":"/mrp-files/399534_240320_gbyqqcq.mrp","size":"449.73KB","len":460526,"vendor":"杭州斯凯","name":"gbyqqcq.mrp","resLen":0,"resInfo":"","resSize":"","id":399534,"detail":"《霸业之妻妾成群》，附身李元霸，当大官，泡MM，挑战天下英豪。"},{"res":"","scr":"240x320","icon":"/mrp-icon/9CPC.png","label":"白发魔女传","version":1015,"down":"/mrp-files/308012_240320_gbfmnz.mrp","size":"344.76KB","len":353030,"vendor":"杭州斯凯","name":"gbfmnz.mrp","resLen":0,"resInfo":"","resSize":"","id":308012,"detail":"练霓裳与武当掌门卓一航相恋，遭人陷害，一夜青丝换白发……"},{"res":"","scr":"240x320","icon":"/mrp-icon/A28P.png","label":"白发魔女传2","version":1004,"down":"/mrp-files/330009_240320_gbfmlba.mrp","size":"396.86KB","len":406385,"vendor":"华益天信","name":"gbfmlba.mrp","resLen":0,"resInfo":"","resSize":"","id":330009,"detail":"魔女暗渡轮回转世重生，再掀恩怨情仇，演绎震撼的仙魔大战。"},{"res":"","scr":"240x320","icon":"/mrp-icon/C6A1.png","label":"白狐","version":1005,"down":"/mrp-files/399681_240320_gbh.mrp","size":"445.18KB","len":455864,"vendor":"南京雅游","name":"gbh.mrp","resLen":0,"resInfo":"","resSize":"","id":399681,"detail":"修真世界，丰富的妖怪，超炫的幻兽，谱写了一场人狐之恋。"}],"now":42}