{"allPages":442,"data":[{"res":"","scr":"240x320","icon":"/mrp-icon/C6N5.png","label":"nes模拟器XL版1.2","version":101,"down":"/mrp-files/xlnes.mrp","size":"37.60KB","len":38501,"vendor":"风的影子","name":"xlnes.mrp","resLen":0,"resInfo":"","resSize":"","id":30001,"detail":"mrpoid专用nes模拟器，把nes放到nes文件夹","md5":"576fe45f4f637128b49134be2ffd1e58"},{"res":"","scr":"240x320","icon":"/mrp-icon/66AV.png","label":"QQ","version":3014,"down":"/mrp-files/qq20081.mrp","size":"42.25KB","len":43268,"vendor":"sky","name":"qq2008.mrp","resLen":0,"resInfo":"","resSize":"","id":203103,"detail":"我的手机，我的QQ，随时随地，想上就上！众多游戏，不容错过。","md5":"0d85f944a402a72370a1d3946167a086"},{"res":"","scr":"240x320","icon":"/mrp-icon/66AV.png","label":"QQ2010","version":3222,"down":"/mrp-files/203203_240320_qq2008.mrp","size":"204.48KB","len":209383,"vendor":"sky","name":"qq2008.mrp","resLen":0,"resInfo":"","resSize":"","id":203103,"detail":"腾讯QQ","md5":"325859f2d233b861054c552c0759bc18"},{"res":"","scr":"240x320","icon":"/mrp-icon/66AV.png","label":"QQ2010","version":3220,"down":"/mrp-files/qq2008.mrp","size":"206.34KB","len":211295,"vendor":"sky","name":"qq2008.mrp","resLen":0,"resInfo":"","resSize":"","id":203103,"detail":"腾讯QQ","md5":"ac648f79c6392e1a10d646137e5fa66d"},{"res":"","scr":"240x320","icon":"/mrp-icon/66AV.png","label":"QQ2010","version":3222,"down":"/mrp-files/203103_240320_qq2008.mrp","size":"204.99KB","len":209909,"vendor":"sky","name":"qq2008.mrp","resLen":0,"resInfo":"","resSize":"","id":203103,"detail":"腾讯QQ","md5":"d47caa5b3ccb0a8678bf9ddd7c32c211"}],"now":26}