{"allPages":436,"data":[{"res":"","scr":"240x320","icon":"/mrp-icon/C6N5.png","label":"超级马里奥","version":1115,"down":"/mrp-files/302022_240320_gcjml.mrp","size":"212.71KB","len":217818,"vendor":"杭州斯凯","name":"gcjml.mrp","resLen":0,"resInfo":"","resSize":"","id":302022,"detail":"超级马里奥，经典再现！让您重温蹦蹦跳跳，踩怪吃币的游戏感动。"},{"res":"","scr":"240x320","icon":"/mrp-icon/95V9.png","label":"超级女生梦工场","version":1032,"down":"/mrp-files/301033_240320_gcjns.mrp","size":"209.07KB","len":214088,"vendor":"杭州斯凯","name":"gcjns.mrp","resLen":0,"resInfo":"","resSize":"","id":301033,"detail":"创造一个完全个性的女生，实现您的梦想！尽在超级女生梦工场！"},{"res":"","scr":"240x320","icon":"/mrp-icon/C6N5.png","label":"超级泡泡堂","version":1005,"down":"/mrp-files/cjppt.mrp","size":"231.71KB","len":237267,"vendor":"杭州斯凯","name":"gppt.mrp","resLen":0,"resInfo":"","resSize":"","id":307024,"detail":"火爆全球的泡泡堂，宝宝，皮蛋，海盗，欢迎您加入战斗队伍！"},{"res":"","scr":"240x320","icon":"/mrp-icon/C6N5.png","label":"超级泡泡堂","version":1024,"down":"/mrp-files/390043_240320_gtppt.mrp","size":"235.87KB","len":241527,"vendor":"杭州斯凯","name":"gtppt.mrp","resLen":0,"resInfo":"","resSize":"","id":390043,"detail":"火爆全球的泡泡堂，宝宝，皮蛋，海盗，欢迎您加入战斗队伍！"},{"res":"","scr":"240x320","icon":"/mrp-icon/C6N5.png","label":"超级泡泡堂","version":1023,"down":"/mrp-files/307024_240320_gppt.mrp","size":"235.93KB","len":241591,"vendor":"杭州斯凯","name":"gppt.mrp","resLen":0,"resInfo":"","resSize":"","id":307024,"detail":"火爆全球的泡泡堂，宝宝，皮蛋，海盗，欢迎您加入战斗队伍！"}],"now":60}