{"allPages":442,"data":[{"res":"","scr":"240x320","icon":"/mrp-icon/C6N5.png","label":"海贼王","version":1006,"down":"/mrp-files/316013_240320_ghzw.mrp","size":"306.54KB","len":313894,"vendor":"美游","name":"ghzw.mrp","resLen":0,"resInfo":"","resSize":"","id":316013,"detail":"海贼王","md5":"7fa07f9ecee8b6c3f5c8b142bc0febf6"},{"res":"","scr":"240x320","icon":"/mrp-icon/C609.png","label":"海贼王:梦想之帆","version":1006,"down":"/mrp-files/399369_240320_ghzwmx.mrp","size":"368.08KB","len":376914,"vendor":"旌德雷霆","name":"ghzwmx.mrp","resLen":0,"resInfo":"","resSize":"","id":399369,"detail":"财富力量，新海贼王时代的序幕已拉开，谁会成为真正的海贼王。","md5":"8b8f70c29e7429ce87004748170910c1"},{"res":"","scr":"240x320","icon":"/mrp-icon/C6CI.png","label":"海贼王正义之战","version":1003,"down":"/mrp-files/399762_240320_gzyzz.mrp","size":"480.36KB","len":491892,"vendor":"南京颂歌","name":"gzyzz.mrp","resLen":0,"resInfo":"","resSize":"","id":399762,"detail":"拥有精美的画面和惊险刺激的战斗，在这里你是真正的海贼王！","md5":"0b897c2fbdc7ef7447db83efc96ee51f"},{"res":"","scr":"240x320","icon":"/mrp-icon/AUIO.png","label":"海战世纪","version":1004,"down":"/mrp-files/359000_240320_ghhsj.mrp","size":"390.27KB","len":399634,"vendor":"杭州斯凯","name":"ghhsj.mrp","resLen":0,"resInfo":"","resSize":"","id":359000,"detail":"激情的海洋战争游戏","md5":"6b63618459d582ab1acadb86499c5685"},{"res":"","scr":"240x320","icon":"/mrp-icon/C6N5.png","label":"韩国超人气布娃娃","version":138,"down":"/mrp-files/17501_240320_rghcr.mrp","size":"214.10KB","len":219236,"vendor":"杭州斯凯","name":"rghcr","resLen":0,"resInfo":"","resSize":"","id":17501,"detail":"韩国人气超旺的布娃娃，绝对是送给女朋友的最佳礼物。","md5":"81115ff653f5b28d924d5e60af12e0b1"}],"now":138}